oplc/__init__.py
oplc/chat.py
oplc-0.0.1.dist-info/LICENSE
oplc-0.0.1.dist-info/METADATA
oplc-0.0.1.dist-info/WHEEL
oplc-0.0.1.dist-info/RECORD
