Metadata-Version: 2.1
Name: oplc
Version: 0.0.1
Summary: 🚀A simple way to use langchain framework.
Home-page: https://github.com/Undertone0809/aslf
License: MIT
Keywords: langchain,aslf,llm,openai,chatgpt,promptulate
Author: aslf
Author-email: zeeland4work@gmail.com
Requires-Python: >=3.8.1,<4.0
Classifier: License :: OSI Approved :: MIT License
Classifier: Programming Language :: Python :: 3
Classifier: Programming Language :: Python :: 3.9
Classifier: Programming Language :: Python :: 3.10
Classifier: Programming Language :: Python :: 3.11
Classifier: Programming Language :: Python :: 3.12
Requires-Dist: langchain (>=0.1.0)
Project-URL: Repository, https://github.com/Undertone0809/aslf
